reqWrapper/__init__.py
reqWrapper/api.py
reqWrapper/model.py
reqWrapper-0.2.1.dist-info/LICENSE
reqWrapper-0.2.1.dist-info/METADATA
reqWrapper-0.2.1.dist-info/WHEEL
reqWrapper-0.2.1.dist-info/top_level.txt
reqWrapper-0.2.1.dist-info/RECORD
